Workbook

Sheet 00_ALL_IN_ONE_TARGET_MASTER
A1: Target Category / Group | B1: Target Page Name | C1: Target URL | D1: Primary Keyword | E1: Secondary & LSI Keywords | F1: Recommended Anchor Text | G1: Anchor Type | H1: Recommended Off-Page Activity | I1: Content Title / Topic Angle | J1: Priority | K1: Execution Status | L1: Notes / Target Intent
A2: 📍 SUB-PART 1: ALWAR LOCAL SEO TARGETS (Footfall & Local Sales)
A3: Alwar Local Target | B3: Zoniraz Alwar Store | C3: https://zoniraz.com/zoniraz-alwar | D3: best jewellery shop in alwar | E3: gold jewellery in alwar, diamond jewellery showroom alwar, bis hallmarked gold alwar | F3: best jewellery shop in Alwar | G3: Local | H3: Local Citations, Google Business Profile Posts, Local Directories | I3: Top Rated Jewellery Shops in Alwar for Wedding Shopping | J3: P1 | K3: Planned | L3: Alwar local store primary landing page
A4: ✈️ SUB-PART 2: EXPORT & B2B TARGETS (Global Trade & Wholesale)
A5: Export / International | B5: Delivery & International Shipping | C5: https://zoniraz.com/delivery | D5: indian jewellery exporter | E5: international jewellery shipping, worldwide gold jewellery delivery, overseas orders | F5: jewellery exporter India | G5: Commercial | H5: B2B Directories, Trade Portals, Export Article Submissions | I5: Sourcing Luxury Certified Gold & Diamond Jewellery from India | J5: P1 | K5: Planned | L5: Overseas shipments & export buyer inquiries
A6: B2B Manufacturing | B6: About Us (Heritage & Purity) | C6: https://zoniraz.com/about | D6: gold jewellery manufacturer india | E6: 50 years jewellery heritage, oem gold manufacturer, bis hallmarked factory purity | F6: gold jewellery manufacturer India | G6: Commercial | H6: Guest Posts, Industry Articles, Brand Press Releases | I6: Custom OEM Gold & Diamond Jewellery Manufacturing Capacity in India | J6: P1 | K6: Planned | L6: Bulk B2B manufacturing & OEM trust
A7: B2B Wholesale Trade | B7: Contact Us (B2B Consultations) | C7: https://zoniraz.com/contact | D7: wholesale diamond jewellery supplier | E7: b2b diamond jewellery supply, bulk diamond jewelry orders | F7: wholesale diamond jewellery supplier | G7: Commercial | H7: Document Sharing, B2B Submissions, Wholesale Portals | I7: Wholesale Diamond Jewellery Supply & Global Exports | J7: P2 | K7: Planned | L7: B2B trade inquiries & catalog requests
A8: B2B Franchise Expansion | B8: Franchise Showroom Dealership | C8: https://zoniraz.com/franchise | D8: jewellery franchise | E8: jewellery showroom franchise, gold jewellery franchise, dealership opportunity | F8: jewellery showroom franchise opportunity | G8: Commercial | H8: Retail Franchise Portals, Guest Posts, Financial Web 2.0 Blogs | I8: How to Open a Profitable Jewellery Showroom Franchise in India | J8: P1 | K8: Planned | L8: B2B showroom franchise dealership expansion
A9: 💼 SUB-PART 3: CORE BRAND & SERVICE PAGES (Authority & High Intent)
A10: Brand Core | B10: Homepage | C10: https://zoniraz.com/ | D10: luxury jewellery brand | E10: bis hallmarked jewellery, certified diamond jewellery online, famous jewellery brands | F10: Zoniraz Jewels | G10: Branded | H10: Social Profiles, High DA Business Directories, Brand Press Releases | I10: Zoniraz Jewels: Premier Luxury Jewellery Brand in India | J10: P1 | K10: Planned | L10: Domain authority & overall brand equity
A11: Gold Exchange Service | B11: Sell Old Gold | C11: https://zoniraz.com/sell-gold | D11: old gold exchange | E11: old gold rate calculator, gold purity valuation, sell old gold online | F11: old gold exchange rate | G11: Commercial | H11: Consumer Advice Articles, Financial Recycling Directories, Forum Q&A | I11: Maximizing Value: How to Safely Exchange Old Gold Jewellery Online | J11: P1 | K11: Planned | L11: High converting old gold recycling service
A12: Gold Savings Scheme | B12: Gold Mine Scheme | C12: https://zoniraz.com/gold-mine | D12: gold saving scheme online | E12: gold monthly installment scheme, gold SIP plan, 10+1 gold savings plan | F12: online gold saving scheme | G12: Exact Match | H12: Personal Finance Web 2.0 Blogs, Savings Scheme Submissions | I12: Smart Financial Habits: Why Monthly Gold Saving Schemes Outperform Cash | J12: P1 | K12: Planned | L12: Monthly recurring gold scheme enrollment
A13: Bullion / Gold Coins | B13: Buy 24K Gold Coins | C13: https://zoniraz.com/buy-gold | D13: buy 24k gold coins | E13: 999 pure gold coins, gold bullion bars, laxmi ganesha gold coin | F13: buy 24k gold coins online | G13: Commercial | H13: Investment Blogs, E-commerce Directory Submissions | I13: Buying 24K 999 Pure Hallmarked Gold Coins Online for Investment | J13: P2 | K13: Planned | L13: Gold coins & bullion investment buyers
A14: Solitaire Vault | B14: Loose Stones Vault | C14: https://zoniraz.com/loose-stones | D14: certified loose diamonds | E14: buy solitaire diamonds, GIA certified loose diamonds, certified gemstones | F14: certified solitaire diamonds | G14: Exact Match | H14: Luxury Jewelry Blogs, Solitaire Customization Forum Threads | I14: Certified Solitaire Diamonds Vault & Custom Ring Crafting | J14: P2 | K14: Planned | L14: High margin certified loose solitaires
A15: 💎 SUB-PART 4: TOP E-COMMERCE CATEGORIES (High Volume Category Sales)
A16: Category Target | B16: Rings Category | C16: https://zoniraz.com/rings | D16: buy diamond rings | E16: diamond engagement ring, gold finger rings, custom bridal ring sets | F16: diamond engagement rings | G16: Partial Match | H16: Fashion & Wedding Blogs, Quora Answers, Pinterest Image Submissions | I16: Latest Gold & Diamond Ring Designs for Women in 2026 | J16: P1 | K16: Planned | L16: Top selling category: Finger & Engagement rings
A17: Category Target | B17: Necklaces Category | C17: https://zoniraz.com/necklaces | D17: luxury bridal necklaces | E17: gold choker necklace, 22k gold bridal set, diamond statement necklace | F17: bridal gold necklaces | G17: Partial Match | H17: Bridal Style Web 2.0, Guest Articles, Image Submissions | I17: Royal 22K Gold & Diamond Bridal Choker Sets for Weddings | J17: P1 | K17: Planned | L17: High ticket bridal necklace category
A18: Category Target | B18: Earrings Category | C18: https://zoniraz.com/earrings | D18: gold hoop earrings for women | E18: gold dangle earrings, traditional jhumkas, diamond stud earrings | F18: gold earrings for women | G18: Commercial | H18: Daily Wear Fashion Articles, PDF Catalog Submissions | I18: Timeless Gold & Diamond Earring Styles for Everyday Luxury | J18: P1 | K18: Planned | L18: High traffic volume category: Studs, Hoops, Jhumkas
A19: Category Target | B19: Solitaires Category | C19: https://zoniraz.com/solitaires | D19: buy certified solitaires | E19: solitaire diamond ring, GIA solitaire pendant, IGI certified loose diamonds | F19: certified solitaire jewelry | G19: Commercial | H19: High-End Luxury Portals, Solitaire Buying Guides | I19: GIA & IGI Certified Solitaire Rings and Earrings Collection | J19: P1 | K19: Planned | L19: Certified Solitaires category
A20: Category Target | B20: Bangles Category | C20: https://zoniraz.com/bangles | D20: 22k gold bangles | E20: traditional gold kangan, diamond bangles, bridal kangan set | F20: 22k gold bangles online | G20: Commercial | H20: Wedding Accessories Guides, Image Sharing | I20: Handcrafted 22K Gold Bridal Bangles and Polki Kangans | J20: P2 | K20: Planned | L20: Bridal & daily gold bangles
A21: 💍 SUB-PART 5: HIGH VALUE PRODUCT TARGETS (Direct E-commerce Conversion)
A22: Product Target | B22: Toni Truelove Ring | C22: https://zoniraz.com/product/toni-truelove-ring-elegant-diamond-ring-for-women | D22: diamond ring for women | E22: elegant diamond ring, 18k gold diamond ring | F22: toni truelove diamond ring | G22: Product Branded | H22: Product Reviews, Image Submissions, Social Bookmarking | I22: Toni Truelove Ring: Elegant Diamond Ring for Women | J22: P1 | K22: Planned | L22: Bestselling women diamond ring
A23: Product Target | B23: Symone Redmond Ring | C23: https://zoniraz.com/product/symone-redmond-ring-luxury-diamond-ring-for-women | D23: luxury diamond ring | E23: designer diamond ring, VS clarity diamond ring | F23: luxury diamond ring for women | G23: Commercial | H23: Product Bookmarking, Luxury Jewelry Reviews | I23: Symone Redmond Ring: Designer Luxury Diamond Band | J23: P1 | K23: Planned | L23: Luxury solitaire style diamond ring
A24: Product Target | B24: Sofian Mens Ring | C24: https://zoniraz.com/product/sofian-ring-stylish-diamond-ring-for-men | D24: mens diamond ring | E24: gents diamond band, 18k white gold mens ring | F24: gents diamond ring design | G24: Commercial | H24: Men's Fashion Blogs, Product Submissions | I24: Sofian Ring: Stylish 18K Diamond Band for Men | J24: P1 | K24: Planned | L24: Top selling male diamond ring
A25: 📝 SUB-PART 6: TOP BLOG & EDITORIAL TARGETS (Informational & Top-Funnel Leads)
A26: Blog Target | B26: Ultimate Bridal Jewellery Guide | C26: https://zoniraz.com/blog/ultimate-bridal-jewellery-guide | D26: ultimate bridal jewellery guide | E26: bridal jewellery set, maang tikka and bangles, wedding lehenga matching | F26: bridal jewellery guide | G26: Informational | H26: Wedding Forums, Bridal Guest Posts, Document Sharing | I26: The Ultimate Indian Bridal Jewellery Guide for Brides of 2026 | J26: P2 | K26: Planned | L26: Bridal shopping & checklist guide
A27: Blog Target | B27: Gold Savings Scheme Guide | C27: https://zoniraz.com/blog/gold-saving-scheme-smartest-investment | D27: gold saving scheme smartest investment | E27: monthly gold SIP, gold chit fund, rupee-cost averaging | F27: monthly gold saving scheme guide | G27: Informational | H27: Personal Finance Web 2.0 Blogs, Investment Articles | I27: Why a Monthly Gold Saving Scheme is the Smartest Investment in 2026 | J27: P2 | K27: Planned | L27: Gold SIP investment guide
A28: Blog Target | B28: Old Gold Exchange Guide | C28: https://zoniraz.com/blog/old-gold-exchange-best-value | D28: old gold exchange best value | E28: exchange old jewellery, gold purity testing, market rates | F28: old gold exchange tips | G28: Informational | H28: Financial Advice Submissions, Consumer Rights Articles | I28: How to Get the Maximum Fair Market Value for Your Old Gold | J28: P2 | K28: Planned | L28: Old gold valuation & exchange guide

Sheet 01_README
A1: ZONIRAZ JEWELLERY — OFF-PAGE SEO & BACKLINK MASTER WORKBOOK
A3: Project Name | B3: Zoniraz Jewellery Off-Page SEO & Backlink Strategy
A4: Website URL | B4: https://zoniraz.com/
A5: Primary Location | B5: Alwar, Rajasthan, India
A6: Purpose | B6: Master structured Excel inventory and campaign tracker for sustainable off-page SEO, local Alwar domination, e-commerce keyword optimization, and high-authority link acquisition.
A7: Source of Truth Rules | B7: 1. Live Website Structure & API Data 2. Sitemaps (sitemap-static, sitemap-categories, sitemap-blogs, sitemap-products) 3. Production API (https://zonirazjewellery.onrender.com/api/admin/products) 4. Zero website/code modifications.
A8: How to Use Workbook | B8: Use 03_EXECUTIVE_SUMMARY for high-level tracking. Use 09_BACKLINK_TARGET_MAP & 10_BACKLINK_CONTENT_PLAN for link building campaigns. Use 18_MONTHLY_BACKLINK_REPORT to log completed backlinks.
A9: Last Audit Date | B9: August 26, 2026
A10: Total Live Products Loaded | B10: 616 Products (100% Catalogue Coverage)

Sheet 02_PROJECT_DETAIL
A1: Parameter | B1: Project Attribute Value
A2: Brand Name | B2: Zoniraz Jewellery
A3: Website URL | B3: https://zoniraz.com/
A4: Business Sector | B4: Luxury BIS Hallmarked Gold & Certified Diamond Jewellery
A5: Primary Location | B5: Alwar, Rajasthan, India
A6: Secondary Markets | B6: Jaipur, Delhi NCR, National India, Global NRI / Overseas Shipping
A7: Core Business Models | B7: Retail E-commerce, Local Store Footfall (Alwar), Old Gold Exchange, Gold Savings Scheme (Gold Mine), Franchise Showroom Dealerships
A8: Target Audience | B8: Brides & Wedding Families, High Net Worth Individuals, Young Professionals, Investors (Gold SIP), B2B Franchise Seekers
A9: Primary SEO Objective | B9: Achieve Page 1 Google visibility for Gold/Diamond Jewellery, Alwar Local Searches, Gold Scheme, Old Gold Exchange & Franchise inquiries.
A10: Backlink Objectives | B10: Build topical authority, local citations, brand mentions, high-quality guest posts, and natural contextual anchors without exact-match over-optimization.

Sheet 03_EXECUTIVE_SUMMARY
A1: Metric / Key Indicator | B1: Count / Value | C1: Notes & Formula Reference
A2: Total Indexable Pages | B2: ==COUNTA('04_PAGE_INVENTORY'!A2:A1000) | C2: Formula: Total rows in 04_PAGE_INVENTORY
A3: Total Static Pages | B3: ==COUNTIF('04_PAGE_INVENTORY'!B2:B1000, "Static") | C3: Formula: Static pages count
A4: Total Local Pages | B4: ==COUNTIF('04_PAGE_INVENTORY'!B2:B1000, "Local") | C4: Formula: Local landing pages count
A5: Total Category Pages | B5: ==COUNTIF('04_PAGE_INVENTORY'!B2:B1000, "Category") | C5: Formula: Category pages count
A6: Total Product Pages | B6: 616 | C6: Retrieved live from production API
A7: Total Blog Pages | B7: ==COUNTA('08_BLOG_KEYWORD_MAP'!A2:A100) | C7: Formula: Blog posts mapped
A8: Total Mapped Keywords | B8: ==COUNTA('05_KEYWORD_MASTER'!A2:A1000) | C8: Formula: Master keyword count
A9: Backlink Target Pages | B9: ==COUNTA('09_BACKLINK_TARGET_MAP'!A2:A100) | C9: Formula: Priority target URLs
A10: Backlink Content Opportunities | B10: ==COUNTA('10_BACKLINK_CONTENT_PLAN'!A2:A200) | C10: Formula: Content briefs created
A11: Alwar Local Keywords | B11: ==COUNTA('12_ALWAR_LOCAL_SEO'!A2:A100) | C11: Formula: Local Alwar strategy keywords
A12: Export / B2B Keywords | B12: ==COUNTA('13_EXPORT_B2B_SEO'!A2:A100) | C12: Formula: B2B / Export strategy keywords
A13: Cannibalization Risks Identified | B13: ==COUNTA('14_CANNIBALIZATION'!A2:A100) | C13: Formula: Flagged cannibalization cases
A14: Missing Target Pages (B2B) | B14: ==COUNTA('15_MISSING_TARGET_PAGES'!A2:A100) | C14: Formula: Unserved keyword intents

Sheet 04_PAGE_INVENTORY
A1: Page ID | B1: Page Type | C1: Page Name | D1: URL | E1: Canonical URL | F1: Indexability | G1: Existing H1 | H1: Existing Title | I1: Existing Meta Description | J1: Intent | K1: Target Location | L1: Commercial Intent | M1: Business Priority | N1: SEO Priority | O1: Backlink Suitability | P1: Notes
A2: P-001 | B2: Static | C2: Homepage | D2: https://zoniraz.com/ | E2: https://zoniraz.com/ | F2: Indexable | G2: Luxury Jewellery House | H2: Zoniraz Jewels | I2: BIS Hallmarked Gold & Certified Diamond Jewellery | J2: Commercial | K2: National / Global | L2: High | M2: P1 | N2: P1 | O2: High | P2: Core homepage
A3: P-002 | B3: Static | C3: About Us | D3: https://zoniraz.com/about | E3: https://zoniraz.com/about | F3: Indexable | G3: About Zoniraz Heritage | H3: About Zoniraz | I3: Luxury Jewellery Brand 50+ years of heritage | J3: Informational | K3: Global | L3: Medium | M3: P3 | N3: P3 | O3: Medium | P3: Trust building
A4: P-003 | B4: Static | C4: Contact Us | D4: https://zoniraz.com/contact | E4: https://zoniraz.com/contact | F4: Indexable | G4: Contact Jewellery Experts | H4: Contact Us | I4: Jewellery Store Support & Appointments | J4: Transactional | K4: Global | L4: High | M4: P2 | N4: P2 | O4: Medium | P4: Lead capture
A5: P-004 | B5: Local | C5: Zoniraz Alwar Store | D5: https://zoniraz.com/zoniraz-alwar | E5: https://zoniraz.com/zoniraz-alwar | F5: Indexable | G5: Best Jewellery Shop in Alwar | H5: Zoniraz Jewellery Store Alwar | I5: Gold & Diamond Jewellery Shop Alwar | J5: Commercial | K5: Alwar, Rajasthan | L5: High | M5: P1 | N5: P1 | O5: High | P5: Local Alwar SEO core target
A6: P-005 | B6: Static | C6: Franchise | D6: https://zoniraz.com/franchise | E6: https://zoniraz.com/franchise | F6: Indexable | G6: Jewellery Franchise Opportunity | H6: Zoniraz Franchise | I6: Gold Jewellery Showroom Franchise India | J6: B2B Commercial | K6: National | L6: High | M6: P1 | N6: P1 | O6: High | P6: B2B Franchise leads
A7: P-006 | B7: Static | C7: Sell Old Gold | D7: https://zoniraz.com/sell-gold | E7: https://zoniraz.com/sell-gold | F7: Indexable | G7: Transparent Old Gold Exchange | H7: Old Gold Exchange | I7: Sell Old Gold Rate Calculator & Valuation | J7: Transactional | K7: National | L7: High | M7: P1 | N7: P1 | O7: High | P7: Old gold recycling service
A8: P-007 | B8: Static | C8: Buy Gold Coins | D8: https://zoniraz.com/buy-gold | E8: https://zoniraz.com/buy-gold | F8: Indexable | G8: 24K Pure Gold Coins | H8: Buy 24K Gold Coins | I8: Gold Bullion & 999 Pure Coins Online | J8: Transactional | K8: National | L8: High | M8: P2 | N8: P2 | O8: Medium | P8: Bullion page
A9: P-008 | B9: Static | C9: Gold Mine Scheme | D9: https://zoniraz.com/gold-mine | E9: https://zoniraz.com/gold-mine | F9: Indexable | G9: 10+1 Gold Mine Savings Plan | H9: Gold Saving Scheme | I9: Gold SIP & Monthly Installment Plan | J9: Transactional | K9: National | L9: High | M9: P1 | N9: P1 | O9: High | P9: Monthly SIP gold scheme
A10: P-009 | B10: Static | C10: Loose Stones | D10: https://zoniraz.com/loose-stones | E10: https://zoniraz.com/loose-stones | F10: Indexable | G10: Standalone Diamond Vault | H10: Loose Stones & Solitaires | I10: Certified Solitaires & Gemstones Vault | J10: Commercial | K10: Global | L10: High | M10: P2 | N10: P2 | O10: High | P10: Loose diamond vault
A11: P-010 | B11: Static | C11: Delivery & Help | D11: https://zoniraz.com/delivery | E11: https://zoniraz.com/delivery | F11: Indexable | G11: Delivery & International Shipping | H11: Delivery & Help Center | I11: Insured Worldwide Jewellery Shipping | J11: Informational | K11: Global | L11: Low | M11: P4 | N11: P4 | O11: Low | P11: Policy page
A12: P-011 | B12: Static | C12: All Collections | D12: https://zoniraz.com/all-collections | E12: https://zoniraz.com/all-collections | F12: Indexable | G12: Editorial Vault Collections | H12: All Collections | I12: Curated Luxury Jewellery Collections | J12: Commercial | K12: Global | L12: Medium | M12: P3 | N12: P3 | O12: Medium | P12: Collections index
... A23: P-022 | B23: Blog Index | C23: Blog Main | D23: https://zoniraz.com/blog | E23: https://zoniraz.com/blog | F23: Indexable | G23: Zoniraz Journal & Studio | H23: Jewellery Journal & Styling Guides | I23: Fashion Bridal Styling & Gold Advice | J23: Informational | K23: Global | L23: Low | M23: P3 | N23: P3 | O23: Medium | P23: Blog index

Sheet 05_KEYWORD_MASTER
A1: Keyword ID | B1: Keyword | C1: Keyword Type | D1: Primary/Secondary/LSI | E1: Search Intent | F1: Target Page | G1: Target URL | H1: Location | I1: Commercial Intent | J1: Business Intent | K1: SEO Priority | L1: Backlink Priority | M1: Cannibalization Risk | N1: Notes
A2: KW-001 | B2: luxury jewellery brand | C2: Brand | D2: Primary | E2: Commercial | F2: Homepage | G2: https://zoniraz.com/ | H2: Global | I2: High | J2: Brand Awareness | K2: P1 | L2: P1 | M2: SAFE | N2: Core brand term
A3: KW-002 | B3: bis hallmarked jewellery | C3: Commercial | D3: Secondary | E3: Transactional | F3: Homepage | G3: https://zoniraz.com/ | H3: National | I3: High | J3: Purity Trust | K3: P1 | L3: P1 | M3: SAFE | N3: Trust signal
A4: KW-003 | B4: certified diamond jewellery online | C4: Commercial | D4: LSI | E4: Transactional | F4: Homepage | G4: https://zoniraz.com/ | H4: Global | I4: High | J4: E-commerce Sales | K4: P1 | L4: P1 | M4: SAFE | N4: Online diamond
A5: KW-004 | B5: best jewellery shop in alwar | C5: Local | D5: Primary | E5: Commercial | F5: Zoniraz Alwar Store | G5: https://zoniraz.com/zoniraz-alwar | H5: Alwar | I5: High | J5: Local Store Visit | K5: P1 | L5: P1 | M5: SAFE | N5: Alwar primary keyword
A6: KW-005 | B6: gold jewellery in alwar | C6: Local | D6: Secondary | E6: Transactional | F6: Zoniraz Alwar Store | G6: https://zoniraz.com/zoniraz-alwar | H6: Alwar | I6: High | J6: Local Gold Sales | K6: P1 | L6: P1 | M6: SAFE | N6: Alwar gold query
A7: KW-006 | B7: diamond jewellery showroom alwar | C7: Local | D7: Secondary | E7: Commercial | F7: Zoniraz Alwar Store | G7: https://zoniraz.com/zoniraz-alwar | H7: Alwar | I7: High | J7: Showroom Visit | K7: P1 | L7: P1 | M7: SAFE | N7: Alwar diamond query
A8: KW-007 | B8: old gold exchange alwar | C8: Local | D8: LSI | E8: Transactional | F8: Zoniraz Alwar Store | G8: https://zoniraz.com/zoniraz-alwar | H8: Alwar | I8: High | J8: Exchange Footfall | K8: P2 | L8: P2 | M8: POSSIBLE | N8: Also relates to /sell-gold
A9: KW-008 | B9: jewellery franchise | C9: B2B | D9: Primary | E9: Commercial | F9: Franchise | G9: https://zoniraz.com/franchise | H9: National | I9: High | J9: Franchise Acquisition | K9: P1 | L9: P1 | M9: SAFE | N9: B2B core keyword
A10: KW-009 | B10: jewellery showroom franchise | C10: B2B | D10: Secondary | E10: Transactional | F10: Franchise | G10: https://zoniraz.com/franchise | H10: National | I10: High | J10: Dealership Leads | K10: P1 | L10: P1 | M10: SAFE | N10: B2B secondary
A11: KW-010 | B11: old gold exchange | C11: Service | D11: Primary | E11: Transactional | F11: Sell Old Gold | G11: https://zoniraz.com/sell-gold | H11: National | I11: High | J11: Gold Recycling | K11: P1 | L11: P1 | M11: SAFE | N11: Primary exchange query
A12: KW-011 | B12: old gold price calculator | C12: Service | D12: Secondary | E12: Informational | F12: Sell Old Gold | G12: https://zoniraz.com/sell-gold | H12: National | I12: High | J12: Calculator Leads | K12: P2 | L12: P2 | M12: SAFE | N12: Tool search
... A23: KW-022 | B23: wholesale diamond jewellery supplier | C23: Wholesale B2B | D23: Secondary | E23: Transactional | F23: Contact Us | G23: https://zoniraz.com/contact | H23: Global | I23: High | J23: Bulk Diamond Sales | K23: P2 | L23: P2 | M23: SAFE | N23: Mapped to /contact

Sheet 06_PRODUCT_KEYWORD_MAP
A1: Product ID | B1: Product Name | C1: Category | D1: Product URL | E1: Primary Keyword | F1: Secondary Keywords | G1: LSI Keywords | H1: Long-tail Keywords | I1: Commercial Keywords | J1: Search Intent | K1: Location Variant | L1: SEO Priority | M1: Backlink Priority
A2: PROD-1787121242351 | B2: Toni Truelove Ring | Elegant Diamond Ring for Women | C2: Rings | D2: https://zoniraz.com/product/toni-truelove-ring-elegant-diamond-ring-for-women | E2: toni truelove ring | F2: rings for women, diamond rings | G2: bis hallmarked rings, 18k yellow gold, rose gold rings | H2: buy toni truelove ring | elegant diamond ring for women online in india | I2: buy rings online, rings price | J2: Transactional | K2: India / Alwar | L2: P1 | M2: P2
A3: PROD-1787121078439 | B3: Symone Redmond Ring | Luxury Diamond Ring for Women | C3: Rings | D3: https://zoniraz.com/product/symone-redmond-ring-luxury-diamond-ring-for-women | E3: symone redmond ring | F3: rings for women, diamond rings | G3: bis hallmarked rings, 18k yellow gold, rose gold rings | H3: buy symone redmond ring | luxury diamond ring for women online in india | I3: buy rings online, rings price | J3: Transactional | K3: India / Alwar | L3: P1 | M3: P2
A4: PROD-1787120901918 | B4: Stefanie Ring | Elegant Diamond Ring for Women | C4: Rings | D4: https://zoniraz.com/product/stefanie-ring-elegant-diamond-ring-for-women | E4: stefanie ring | F4: rings for women, diamond rings | G4: bis hallmarked rings, 18k yellow gold, rose gold rings | H4: buy stefanie ring | elegant diamond ring for women online in india | I4: buy rings online, rings price | J4: Transactional | K4: India / Alwar | L4: P1 | M4: P2
A5: PROD-1787120734271 | B5: Sofian Ring | Stylish Diamond Ring for Men | C5: Rings | D5: https://zoniraz.com/product/sofian-ring-stylish-diamond-ring-for-men | E5: sofian ring | F5: rings for women, diamond rings | G5: bis hallmarked rings, 18k yellow gold, rose gold rings | H5: buy sofian ring | stylish diamond ring for men online in india | I5: buy rings online, rings price | J5: Transactional | K5: India / Alwar | L5: P1 | M5: P2
A6: PROD-1787120563511 | B6: Simone Earring | Elegant Diamond Earrings for Women | C6: Earrings | D6: https://zoniraz.com/product/simone-earring-elegant-diamond-earrings-for-women | E6: simone earring | F6: earrings for women, stud earrings earrings | G6: bis hallmarked earrings, 18k yellow gold, rose gold earrings | H6: buy simone earring | elegant diamond earrings for women online in india | I6: buy earrings online, earrings price | J6: Transactional | K6: India / Alwar | L6: P1 | M6: P2
A7: PROD-1787120363143 | B7: Sharon Athey Ring | Elegant Diamond Ring for Women | C7: Rings | D7: https://zoniraz.com/product/sharon-athey-ring-elegant-diamond-ring-for-women | E7: sharon athey ring | F7: rings for women, diamond rings | G7: bis hallmarked rings, 18k yellow gold, rose gold rings | H7: buy sharon athey ring | elegant diamond ring for women online in india | I7: buy rings online, rings price | J7: Transactional | K7: India / Alwar | L7: P1 | M7: P2
A8: PROD-1787120090943 | B8: Rhea Ring | Elegant Diamond Ring for Women | C8: Rings | D8: https://zoniraz.com/product/rhea-ring-elegant-diamond-ring-for-women | E8: rhea ring | F8: rings for women, diamond rings | G8: bis hallmarked rings, 18k yellow gold, rose gold rings | H8: buy rhea ring | elegant diamond ring for women online in india | I8: buy rings online, rings price | J8: Transactional | K8: India / Alwar | L8: P1 | M8: P2
A9: PROD-1787119811184 | B9: Natalie Ring | Elegant Diamond Ring for Women | C9: Rings | D9: https://zoniraz.com/product/natalie-ring-elegant-diamond-ring-for-women | E9: natalie ring | F9: rings for women, diamond rings | G9: bis hallmarked rings, 18k yellow gold, rose gold rings | H9: buy natalie ring | elegant diamond ring for women online in india | I9: buy rings online, rings price | J9: Transactional | K9: India / Alwar | L9: P1 | M9: P2
A10: PROD-1787119122864 | B10: Molly Lappegaard Ring | Designer Diamond Ring for Women | C10: Rings | D10: https://zoniraz.com/product/molly-lappegaard-ring-designer-diamond-ring-for-women | E10: molly lappegaard ring | F10: rings for women, diamond rings | G10: bis hallmarked rings, 18k yellow gold, rose gold rings | H10: buy molly lappegaard ring | designer diamond ring for women online in india | I10: buy rings online, rings price | J10: Transactional | K10: India / Alwar | L10: P1 | M10: P2
A11: PROD-1787118915953 | B11: Meg Ellis Ring | Elegant Diamond Ring for Women | C11: Rings | D11: https://zoniraz.com/product/meg-ellis-ring-elegant-diamond-ring-for-women | E11: meg ellis ring | F11: rings for women, diamond rings | G11: bis hallmarked rings, 18k yellow gold, rose gold rings | H11: buy meg ellis ring | elegant diamond ring for women online in india | I11: buy rings online, rings price | J11: Transactional | K11: India / Alwar | L11: P1 | M11: P2
A12: PROD-1787118722273 | B12: Markus Ring | Stylish Diamond Ring for women | C12: Rings | D12: https://zoniraz.com/product/markus-ring-stylish-diamond-ring-for-women | E12: markus ring | F12: rings for women, diamond rings | G12: bis hallmarked rings, 18k yellow gold, rose gold rings | H12: buy markus ring | stylish diamond ring for women online in india | I12: buy rings online, rings price | J12: Transactional | K12: India / Alwar | L12: P1 | M12: P2
... A617: PROD-1784111885503 | B617: Diamond Starburst Evil Eye Pendant | Zoniraz | C617: Pendants | D617: https://zoniraz.com/product/diamond-starburst-evil-eye-pendant-zoniraz | E617: diamond starburst evil eye pendant | F617: pendants for women, diamond pendants | G617: bis hallmarked pendants, 18k yellow gold, rose gold, white gold pendants | H617: buy diamond starburst evil eye pendant | zoniraz online in india | I617: buy pendants online, pendants price | J617: Transactional | K617: India / Alwar | L617: P3 | M617: P4

Sheet 07_CATEGORY_KEYWORD_MAP
A1: Category | B1: URL | C1: Primary Keyword | D1: Secondary Keywords | E1: LSI Keywords | F1: Long-tail Keywords | G1: Commercial Keywords | H1: Local Keywords | I1: Intent | J1: SEO Priority | K1: Backlink Priority
A2: Rings | B2: https://zoniraz.com/rings | C2: buy diamond rings | D2: diamond engagement ring, gold finger rings | E2: bridal ring sets, solitaire rings, mens gold ring | F2: latest gold ring designs for women with price | G2: buy custom diamond engagement rings online | H2: gold rings in Alwar | I2: Transactional | J2: P1 | K2: P1
A3: Earrings | B3: https://zoniraz.com/earrings | C3: gold hoop earrings for women | D3: gold dangle earrings, traditional jhumkas | E3: diamond stud earrings, mini huggie hoops | F3: lightweight 22k gold hoop earrings for daily wear | G3: buy hallmarked gold jhumkas online | H3: gold earrings shop in Alwar | I3: Transactional | J3: P1 | K3: P1
A4: Pendants | B4: https://zoniraz.com/pendants | C4: gold pendant necklace | D4: diamond pendant for women, initial necklace | E4: solitaire diamond pendant, Om gold pendant | F4: gold pendant necklace layering for women | G4: buy diamond initial pendant online | H4: gold pendant in Alwar | I4: Transactional | J4: P2 | K4: P2
A5: Necklaces | B5: https://zoniraz.com/necklaces | C5: luxury bridal necklaces | D5: gold choker necklace, 22k gold bridal set | E5: diamond statement necklace, long satlada | F5: royal 22k gold bridal choker necklace set | G5: buy hallmarked gold bridal necklace online | H5: bridal jewellery in Alwar | I5: Transactional | J5: P1 | K5: P1
A6: Bangles | B6: https://zoniraz.com/bangles | C6: 22k gold bangles | D6: traditional gold kangan, diamond bangles | E6: polki bangles set, everyday lightweight gold bangles | F6: handcrafted 22k gold bridal bangle set of 7 | G6: buy certified gold bangles online | H6: gold bangles shop in Alwar | I6: Transactional | J6: P2 | K6: P2
A7: Bracelets | B7: https://zoniraz.com/bracelets | C7: diamond tennis bracelet | D7: 18k gold chain bracelet, womens charm bracelet | E7: diamond cuff bracelet, flexible gold bracelet | F7: luxury 18k gold diamond tennis bracelet for women | G7: buy certified diamond bracelet online | H7: diamond bracelet in Alwar | I7: Transactional | J7: P2 | K7: P2
A8: Mangalsutras | B8: https://zoniraz.com/mangalsutras | C8: gold diamond mangalsutra | D8: modern short mangalsutra, traditional black bead | E8: 18k diamond mangalsutra pendant, daily wear | F8: lightweight single diamond mangalsutra design | G8: buy hallmarked gold mangalsutra online | H8: gold mangalsutra in Alwar | I8: Transactional | J8: P2 | K8: P2
A9: Nose Pins | B9: https://zoniraz.com/nose-pins | C9: buy diamond nose pin | D9: single stone diamond nose stud, gold floral pin | E9: 14k gold diamond nose ring, press on nose stud | F9: certified VS diamond nose pin online in India | G9: buy gold diamond nose pin online | H9: diamond nose pin in Alwar | I9: Transactional | J9: P3 | K9: P3
A10: Solitaires | B10: https://zoniraz.com/solitaires | C10: buy certified solitaires | D10: solitaire diamond ring, GIA solitaire pendant | E10: IGI certified loose diamonds, VVS solitaire studs | F10: buy GIA certified single diamond solitaire ring | G10: buy certified solitaire jewelry online | H10: solitaire diamonds in Alwar | I10: Transactional | J10: P1 | K10: P1
A11: Gold Coins | B11: https://zoniraz.com/gold-coins | C11: buy 24k gold coins | D11: 999 pure gold coins, Laxmi Ganesha gold coin | E11: 1g 2g 5g 10g gold coin, gold bullion bar | F11: tamper proof 24k 999 pure gold coin 10 gram | G11: buy 24k gold coins online with hallmark | H11: gold coins in Alwar | I11: Transactional | J11: P2 | K11: P2

Sheet 08_BLOG_KEYWORD_MAP
A1: Blog Title | B1: URL | C1: Topic | D1: Primary Keyword | E1: Secondary Keywords | F1: LSI Keywords | G1: Long-tail Keywords | H1: Search Intent | I1: SEO Priority | J1: Backlink Priority
A2: 10 Timeless Gold Earring Styles Every Woman Must Own in 2026 | B2: https://zoniraz.com/blog/timeless-gold-earring-styles-2026 | C2: Earring Styling | D2: timeless gold earring styles | E2: gold studs, diamond drops, gold hoops, jhumkas | F2: 18k 22k gold purity, BIS hallmark 916 | G2: 10 timeless gold earring styles for women 2026 | H2: Informational | I2: P3 | J2: P3
A3: The Ultimate Bridal Jewellery Guide: From Maang Tikka to Bangles | B3: https://zoniraz.com/blog/ultimate-bridal-jewellery-guide | C3: Bridal Buying Guide | D3: ultimate bridal jewellery guide | E3: maang tikka, bridal necklace set, chandbalis, bangles | F3: lehenga matching jewellery, polki diamond choker | G3: complete Indian bridal jewellery buying guide | H3: Informational | I3: P2 | J3: P2
A4: Gold Saving Scheme: The Smartest Way to Invest in Gold Monthly | B4: https://zoniraz.com/blog/gold-saving-scheme-smartest-investment | C4: Gold SIP Investment | D4: gold saving scheme smartest investment | E4: monthly gold SIP, gold chit fund, Zoniraz Gold Mine | F4: rupee-cost averaging, gold price fluctuation, 10+1 scheme | G4: how to start monthly gold saving scheme in India | H4: Informational | I4: P2 | J4: P2
A5: Old Gold Exchange: How to Get the Best Value for Your Old Jewellery | B5: https://zoniraz.com/blog/old-gold-exchange-best-value | C5: Gold Exchange Guide | D5: old gold exchange best value | E5: exchange old jewellery, gold purity testing, market rates | F5: XRF gold testing, zero deduction old gold exchange | G5: how to get highest value when exchanging old gold | H5: Informational | I5: P2 | J5: P2
A6: Gold Pendant Necklaces: The Art of Layering for Every Occasion | B6: https://zoniraz.com/blog/gold-pendant-necklace-layering-guide | C6: Necklace Layering | D6: gold pendant necklace layering guide | E6: layering gold chains, solitaire diamond pendant, Om pendant | F6: 14-16 inch choker, 18-20 inch pendant, 22-24 inch chain | G6: step by step guide to layering gold pendant necklaces | H6: Informational | I6: P3 | J6: P3

Sheet 09_BACKLINK_TARGET_MAP
A1: Target ID | B1: Target Page | C1: Target URL | D1: Page Type | E1: Primary Keyword | F1: Secondary Keywords | G1: LSI Keywords | H1: Search Intent | I1: Target Location | J1: Business Intent | K1: Priority | L1: Backlink Suitability | M1: Reason
A2: TGT-001 | B2: Homepage | C2: https://zoniraz.com/ | D2: Static Homepage | E2: luxury jewellery brand | F2: bis hallmarked jewellery, famous jewellery brands | G2: designer diamond jewellery, trusted showroom | H2: Commercial | I2: Global | J2: Brand Awareness | K2: P1 | L2: High | M2: Core brand authority & domain rating
A3: TGT-002 | B3: Alwar Local Store | C3: https://zoniraz.com/zoniraz-alwar | D3: Local Landing | E3: best jewellery shop in alwar | F3: gold jewellery in alwar, diamond jewellery in alwar | G3: jewellery showroom in alwar, bis gold alwar | H3: Local Commercial | I3: Alwar | J3: Local Footfall & Sales | K3: P1 | L3: High | M3: Local SEO target #1 for Alwar store
A4: TGT-003 | B4: Franchise | C4: https://zoniraz.com/franchise | D4: B2B Service | E4: jewellery franchise | F4: jewellery showroom franchise, gold jewellery franchise | G4: jewellery business franchise, dealership | H4: B2B Commercial | I4: National | J4: Franchise Lead Gen | K4: P1 | L4: High | M4: High margin B2B showroom franchise leads
A5: TGT-004 | B5: Sell Old Gold | C5: https://zoniraz.com/sell-gold | D5: Service | E5: old gold exchange | F5: old gold calculator, old gold rate | G5: sell old gold online, gold valuation | H5: Transactional | I5: National | J5: Gold Recycling Leads | K5: P1 | L5: High | M5: High converting old gold exchange service
A6: TGT-005 | B6: Gold Mine Scheme | C6: https://zoniraz.com/gold-mine | D6: Scheme | E6: gold saving scheme online | F6: gold monthly installment scheme, gold SIP plan | G6: systematic gold investment, flexible gold plan | H6: Transactional | I6: National | J6: Recurring SIP Revenue | K6: P1 | L6: High | M6: Recurring monthly scheme subscriber acquisition
A7: TGT-006 | B7: Rings Category | C7: https://zoniraz.com/rings | D7: Category | E7: buy diamond rings | F7: diamond engagement ring, custom gold rings | G7: bridal ring sets, lab created diamond rings | H7: Commercial | I7: Global | J7: E-commerce Category Sales | K7: P1 | L7: High | M7: Top selling category page
A8: TGT-007 | B8: Necklaces Category | C8: https://zoniraz.com/necklaces | D8: Category | E8: luxury bridal necklaces | F8: gold choker necklace, 22k gold necklace | G8: royal bridal set, diamond statement necklace | H8: Commercial | I8: Global | J8: High Ticket Sales | K8: P1 | L8: High | M8: High ticket bridal necklace category
A9: TGT-008 | B9: Earrings Category | C9: https://zoniraz.com/earrings | D9: Category | E9: gold hoop earrings for women | F9: gold dangle earrings, traditional jhumkas | G9: diamond studs, huggie earrings | H9: Commercial | I9: Global | J9: E-commerce Sales | K9: P2 | L9: High | M9: High traffic volume category
A10: TGT-009 | B10: Loose Stones Vault | C10: https://zoniraz.com/loose-stones | D10: Vault Service | E10: certified loose diamonds | F10: buy solitaire diamonds, certified gemstones | G10: IGI diamonds, GIA solitaire ring | H10: Commercial | I10: Global | J10: Solitaire Sales | K10: P2 | L10: High | M10: High margin solitaire diamond buyers
A11: TGT-010 | B11: Bridal Blog Guide | C11: https://zoniraz.com/blog/ultimate-bridal-jewellery-guide | D11: Blog Article | E11: ultimate bridal jewellery guide | F11: bridal jewellery set, maang tikka and bangles | G11: bridal jewellery planning, wedding jewelry | H11: Informational | I11: Global | J11: Top-of-Funnel Leads | K11: P3 | L11: Medium | M11: Informational link building target

Sheet 10_BACKLINK_CONTENT_PLAN
A1: Content ID | B1: Activity Type | C1: Target Page | D1: Target URL | E1: Primary Keyword | F1: Secondary Keywords | G1: LSI Keywords | H1: Anchor Text | I1: Anchor Type | J1: Content Topic | K1: Content Title | L1: Content Description | M1: Content Angle | N1: Search Intent | O1: Location | P1: Priority | Q1: Status | R1: Published URL | S1: Date | T1: Notes
A2: CNT-001 | B2: Local Citation | C2: Alwar Page | D2: https://zoniraz.com/zoniraz-alwar | E2: best jewellery shop in alwar | F2: gold jewellery in alwar | G2: jewellery showroom alwar | H2: Zoniraz Jewellery Store Alwar | I2: Local | J2: Top Jewellery Showrooms in Alwar | K2: Top Rated Jewellery Shops in Alwar for Wedding Shopping | L2: Directory listing documenting Zoniraz Alwar showroom location, hallmark purity, and contact details. | M2: Local Business Profile | N2: Commercial | O2: Alwar | P2: P1 | Q2: Planned | T2: Local Alwar citation
A3: CNT-002 | B3: Guest Post | C3: Franchise | D3: https://zoniraz.com/franchise | E3: jewellery franchise | F3: jewellery brand franchise | G3: jewellery business opportunity | H3: jewellery showroom franchise | I3: Commercial | J3: Retail Franchise Opportunities | K3: How to Open a Profitable Jewellery Showroom Franchise in India | L3: Educational guide discussing investment returns, margin, and brand support in luxury retail franchises. | M3: B2B Investment | N3: Commercial | O3: India | P3: P1 | Q3: Planned | T3: Guest post on retail blog
A4: CNT-003 | B4: Web 2.0 Blog | C4: Gold Mine | D4: https://zoniraz.com/gold-mine | E4: gold saving scheme online | F4: gold monthly installment scheme | G4: gold SIP plan | H4: online gold saving scheme | I4: Exact Match | J4: Personal Finance & Wealth | K4: Smart Financial Habits: Why Monthly Gold Saving Schemes Outperform Cash | L4: Comparison of physical gold accumulation via monthly installments vs idle cash savings. | M4: Wealth Building | N4: Informational | O4: National | P4: P1 | Q4: Planned | T4: Finance Web 2.0
A5: CNT-004 | B5: Article Submission | C5: Sell Gold | D5: https://zoniraz.com/sell-gold | E5: old gold exchange | F5: old gold rate calculator | G5: gold purity valuation | H5: old gold exchange process | I5: Partial Match | J5: Financial Recycling | K5: Maximizing Value: How to Safely Exchange Old Gold Jewellery Online | L5: Detailed breakdown of BIS hallmarked testing, live valuation rates, and avoiding deductions. | M5: Consumer Advice | N5: Informational | O5: National | P5: P2 | Q5: Planned | T5: Article directory submission
A6: CNT-005 | B6: Quora Forum | C6: Rings Category | D6: https://zoniraz.com/rings | E6: diamond engagement ring | F6: bridal ring sets | G6: custom engagement ring | H6: diamond engagement rings | I6: Partial Match | J6: Engagement Ring Choice | K6: What to Look for When Choosing a Diamond Engagement Ring? | L6: Informational response breaking down the 4Cs (Cut, Clarity, Color, Carat) and setting choices. | M6: Expert Advice | N6: Informational | O6: Global | P6: P2 | Q6: Planned | T6: Quora response

Sheet 11_ANCHOR_TEXT_PLAN
A1: Target Page | B1: Target URL | C1: Primary Keyword | D1: Branded Anchor | E1: Naked URL | F1: Partial Match | G1: Natural / Contextual | H1: Generic | I1: Local | J1: Commercial | K1: Exact Match
A2: Homepage | B2: https://zoniraz.com/ | C2: luxury jewellery brand | D2: Zoniraz Jewels | E2: https://zoniraz.com/ | F2: Zoniraz luxury jewellery | G2: explore hallmarked gold designs at Zoniraz | H2: visit official site | I2: Zoniraz jewellery brand India | J2: buy certified diamond jewellery | K2: luxury jewellery brand
A3: Alwar Store | B3: https://zoniraz.com/zoniraz-alwar | C3: best jewellery shop in alwar | D3: Zoniraz Alwar | E3: https://zoniraz.com/zoniraz-alwar | F3: Zoniraz jewellery store in Alwar | G3: leading gold showroom located in Alwar | H3: view store details | I3: best jewellery shop in Alwar | J3: buy gold jewellery in Alwar | K3: jewellery shop in Alwar
A4: Franchise | B4: https://zoniraz.com/franchise | C4: jewellery franchise | D4: Zoniraz Franchise | E4: https://zoniraz.com/franchise | F4: Zoniraz showroom franchise | G4: expanding luxury jewellery retail network | H4: apply for franchise | I4: jewellery franchise in India | J4: jewellery showroom franchise opportunity | K4: jewellery franchise
A5: Sell Old Gold | B5: https://zoniraz.com/sell-gold | C5: old gold exchange | D5: Zoniraz Gold Exchange | E5: https://zoniraz.com/sell-gold | F5: Zoniraz old gold valuation | G5: transparent old gold testing and exchange | H5: check gold rate | I5: old gold exchange in Alwar | J5: sell old gold at live market rates | K5: old gold exchange
A6: Gold Mine | B6: https://zoniraz.com/gold-mine | C6: gold saving scheme online | D6: Zoniraz Gold Mine | E6: https://zoniraz.com/gold-mine | F6: Zoniraz 10+1 gold savings plan | G6: monthly gold investment scheme with bonus | H6: enroll in scheme | I6: gold savings plan Alwar | J6: online gold monthly installment scheme | K6: gold saving scheme online

Sheet 12_ALWAR_LOCAL_SEO
A1: Keyword | B1: Target Page | C1: Target URL | D1: Keyword Type | E1: Intent | F1: Anchor Text | G1: Content Topic | H1: Content Title | I1: Content Description | J1: Activity Type | K1: Priority
A2: best jewellery shop in alwar | B2: Zoniraz Alwar Store | C2: https://zoniraz.com/zoniraz-alwar | D2: Local Commercial | E2: Commercial | F2: best jewellery shop in Alwar | G2: Alwar Retail Guide | H2: Top Rated Jewellery Shops in Alwar Rajasthan | I2: Directory listing focusing on Zoniraz Alwar store location and customer reviews. | J2: Local Citation | K2: P1
A3: gold jewellery in alwar | B3: Zoniraz Alwar Store | C3: https://zoniraz.com/zoniraz-alwar | D3: Local Transactional | E3: Transactional | F3: gold jewellery in Alwar | G3: Gold Buyers Alwar | H3: Where to Buy 22K Hallmarked Gold Jewellery in Alwar | I3: Article highlighting 916 hallmarked purity and gold rate transparency in Alwar. | J3: Article Submission | K3: P1
A4: diamond jewellery showroom alwar | B4: Zoniraz Alwar Store | C4: https://zoniraz.com/zoniraz-alwar | D4: Local Commercial | E4: Commercial | F4: diamond jewellery showroom Alwar | G4: Diamond Showrooms Alwar | H4: Certified Diamond Jewellery Showroom Guide for Alwar | I4: Focusing on IGI certified diamond rings and necklaces available in Alwar store. | J4: Web 2.0 Blog | K4: P1
A5: old gold exchange alwar | B5: Zoniraz Alwar Store | C5: https://zoniraz.com/zoniraz-alwar | D5: Local Transactional | E5: Transactional | F5: old gold exchange Alwar | G5: Old Gold Exchange Alwar | H5: How to Exchange Old Gold for New Jewellery in Alwar | I5: Guide on XRF gold testing and instant cash valuation in Alwar store. | J5: PDF Submission | K5: P2

Sheet 13_EXPORT_B2B_SEO
A1: Keyword | B1: Target Page | C1: Target URL | D1: Intent | E1: Keyword Type | F1: Anchor Text | G1: Content Topic | H1: Content Title | I1: Content Description | J1: Activity Type | K1: Priority | L1: Target Page Status
A2: indian jewellery exporter | B2: Delivery & International Shipping | C2: https://zoniraz.com/delivery | D2: Commercial B2B | E2: Export | F2: jewellery exporter India | G2: Global Jewellery Trade | H2: Sourcing Luxury Certified Gold & Diamond Jewellery from India | I2: Content brief targeting overseas importers and wholesale distributors linking to Delivery & International Shipping page. | J2: B2B Directory | K2: P1 | L2: Mapped to /delivery
A3: gold jewellery manufacturer india | B3: About Us (Manufacturing Heritage) | C3: https://zoniraz.com/about | D3: Commercial B2B | E3: Manufacturer | F3: gold jewellery manufacturer India | G3: OEM Manufacturing | H3: Custom OEM Gold & Diamond Jewellery Manufacturing Capacity in India | I3: Content brief targeting bulk buyers seeking factory OEM manufacturing linking to About Us heritage page. | J3: Guest Post | K3: P1 | L3: Mapped to /about
A4: wholesale diamond jewellery supplier | B4: Contact Us (B2B Inquiries) | C4: https://zoniraz.com/contact | D4: Transactional B2B | E4: Wholesale | F4: wholesale diamond jewellery supplier | G4: B2B Wholesale Supply | H4: Wholesale Diamond Jewellery Supply & Global Exports | I4: Targeting retail jewelers looking for certified diamond inventory supply linking to Contact page. | J4: Document Sharing | K4: P2 | L4: Mapped to /contact
A5: jewellery showroom franchise | B5: Franchise Showroom Dealership | C5: https://zoniraz.com/franchise | D5: Commercial B2B | E5: Franchise | F5: jewellery showroom franchise | G5: Retail Franchise | H5: Luxury Jewellery Showroom Franchise Opportunity in India | I5: B2B franchise showroom partnership guide linking to Franchise page. | J5: Guest Post | K5: P1 | L5: Mapped to /franchise

Sheet 14_CANNIBALIZATION
A1: Keyword | B1: Page 1 | C1: URL 1 | D1: Page 2 | E1: URL 2 | F1: Risk | G1: Reason | H1: Recommendation
A2: old gold exchange | B2: Sell Gold Page | C2: https://zoniraz.com/sell-gold | D2: Blog Article | E2: https://zoniraz.com/blog/old-gold-exchange-best-value | F2: POSSIBLE | G2: Both pages target the exact term "old gold exchange". | H2: Keep /sell-gold as primary transactional target and link blog post to /sell-gold.
A3: gold saving scheme | B3: Gold Mine Page | C3: https://zoniraz.com/gold-mine | D3: Blog Article | E3: https://zoniraz.com/blog/gold-saving-scheme-smartest-investment | F3: POSSIBLE | G3: Both target gold SIP scheme search queries. | H3: Maintain /gold-mine for direct enrollment and use blog post for educational support.
A4: buy 24k gold coins | B4: Gold Coins Category | C4: https://zoniraz.com/gold-coins | D4: Buy Gold Static | E4: https://zoniraz.com/buy-gold | F4: HIGH CANNIBALIZATION | G4: Duplicate URLs targeting gold coin purchasing. | H4: Set canonical tag on /buy-gold pointing to /gold-coins or consolidate content.
A5: gold jewellery in alwar | B5: Alwar Local Page | C5: https://zoniraz.com/zoniraz-alwar | D5: Homepage | E5: https://zoniraz.com/ | F5: SAFE | G5: Distinct local geo-targeting vs national homepage. | H5: Keep local backlink anchors targeted strictly to /zoniraz-alwar.

Sheet 15_MISSING_TARGET_PAGES
A1: Keyword | B1: Intent | C1: Recommended Page Type | D1: Reason | E1: Priority
A2: indian jewellery exporter | B2: Commercial B2B | C2: Dedicated B2B Export Page | D2: Currently no page targets international trade buyers or overseas export clients. | E2: P1
A3: gold jewellery manufacturer india | B3: Commercial B2B | C3: OEM Manufacturing Page | D3: Currently no page documents factory manufacturing capacity or B2B bulk supply. | E3: P1
A4: wholesale diamond jewellery supplier | B4: Transactional B2B | C4: Wholesale B2B Catalog Page | D4: B2B diamond jewelry buyers have no designated landing page or inquiry form. | E4: P2

Sheet 16_DATA_VALIDATION
A1: Issue Type | B1: Item | C1: URL / Keyword | D1: Source | E1: Issue Description | F1: Severity | G1: Recommendation | H1: Status
A2: Duplicate Intent | B2: Gold Coins Page | C2: https://zoniraz.com/buy-gold vs /gold-coins | D2: Sitemap audit | E2: Two separate URLs targeting 24K gold coin buyers. | F2: HIGH | G2: Consolidate content or set canonical header to /gold-coins. | H2: Needs Review
A3: Missing B2B Page | B3: Export Keywords | C3: indian jewellery exporter | D3: Keyword Audit | E3: High search volume B2B keywords have no target landing page on website. | F3: HIGH | G3: Create future /b2b-export landing page. | H3: Planned
A4: Product Coverage | B4: Live Catalogue API | C4: https://zonirazjewellery.onrender.com/api/admin/products | D4: Production API | E4: Verified live product catalogue count. | F4: LOW | G4: 100% catalog (616 products) included in sheet 06_PRODUCT_KEYWORD_MAP. | H4: Verified

Sheet 17_OUTPUT_TRACKING
A1: Metric | B1: Baseline | C1: Month 1 | D1: Month 2 | E1: Month 3 | F1: Month 4 | G1: Month 5 | H1: Month 6 | I1: Change | J1: Notes
A2: Organic Traffic (Monthly) | B2: 1200 | I2: ==H2-B2 | J2: Google Analytics 4
A3: Organic Lead Enquiries | B3: 45 | I3: ==H3-B3 | J3: Form & WhatsApp leads
A4: Total Keywords Mapped | B4: 135 | I4: ==H4-B4 | J4: Keyword master
A5: Top 3 Ranking Keywords | B5: 8 | I5: ==H5-B5 | J5: Google Search Console
A6: Top 10 Ranking Keywords | B6: 24 | I6: ==H6-B6 | J6: GSC Page 1 positions
A7: Alwar Local Store Rankings | B7: 3 | I7: ==H7-B7 | J7: Local pack position
A8: Referring Domains | B8: 42 | I8: ==H8-B8 | J8: Ahrefs / Moz
A9: Total Backlinks Built | B9: 110 | I9: ==H9-B9 | J9: Verified live links

Sheet 18_MONTHLY_BACKLINK_REPORT
A1: Activity Type | B1: Monthly Target | C1: Month 1 | D1: Month 2 | E1: Month 3 | F1: Month 4 | G1: Month 5 | H1: Month 6 | I1: Total Done | J1: Remaining | K1: Notes
A2: Profile Creation | B2: 20 | C2: 0 | D2: 0 | E2: 0 | F2: 0 | G2: 0 | H2: 0 | I2: ==SUM(C2:H2) | J2: ==B2-I2 | K2: Active campaign tracking
A3: Business Directory Listing | B3: 25 | C3: 0 | D3: 0 | E3: 0 | F3: 0 | G3: 0 | H3: 0 | I3: ==SUM(C3:H3) | J3: ==B3-I3 | K3: Active campaign tracking
A4: Local Citation | B4: 30 | C4: 0 | D4: 0 | E4: 0 | F4: 0 | G4: 0 | H4: 0 | I4: ==SUM(C4:H4) | J4: ==B4-I4 | K4: Active campaign tracking
A5: Google Business Profile Post | B5: 15 | C5: 0 | D5: 0 | E5: 0 | F5: 0 | G5: 0 | H5: 0 | I5: ==SUM(C5:H5) | J5: ==B5-I5 | K5: Active campaign tracking
A6: Web 2.0 Blog | B6: 10 | C6: 0 | D6: 0 | E6: 0 | F6: 0 | G6: 0 | H6: 0 | I6: ==SUM(C6:H6) | J6: ==B6-I6 | K6: Active campaign tracking
A7: Article Submission | B7: 12 | C7: 0 | D7: 0 | E7: 0 | F7: 0 | G7: 0 | H7: 0 | I7: ==SUM(C7:H7) | J7: ==B7-I7 | K7: Active campaign tracking
A8: Guest Post | B8: 5 | C8: 0 | D8: 0 | E8: 0 | F8: 0 | G8: 0 | H8: 0 | I8: ==SUM(C8:H8) | J8: ==B8-I8 | K8: Active campaign tracking
A9: Quora & Forum Participation | B9: 20 | C9: 0 | D9: 0 | E9: 0 | F9: 0 | G9: 0 | H9: 0 | I9: ==SUM(C9:H9) | J9: ==B9-I9 | K9: Active campaign tracking
A10: Social Bookmarking | B10: 30 | C10: 0 | D10: 0 | E10: 0 | F10: 0 | G10: 0 | H10: 0 | I10: ==SUM(C10:H10) | J10: ==B10-I10 | K10: Active campaign tracking
A11: PDF & PPT Submission | B11: 10 | C11: 0 | D11: 0 | E11: 0 | F11: 0 | G11: 0 | H11: 0 | I11: ==SUM(C11:H11) | J11: ==B11-I11 | K11: Active campaign tracking
A12: Image Submission | B12: 15 | C12: 0 | D12: 0 | E12: 0 | F12: 0 | G12: 0 | H12: 0 | I12: ==SUM(C12:H12) | J12: ==B12-I12 | K12: Active campaign tracking
A13: Video Submission | B13: 5 | C13: 0 | D13: 0 | E13: 0 | F13: 0 | G13: 0 | H13: 0 | I13: ==SUM(C13:H13) | J13: ==B13-I13 | K13: Active campaign tracking
A14: Document Sharing | B14: 10 | C14: 0 | D14: 0 | E14: 0 | F14: 0 | G14: 0 | H14: 0 | I14: ==SUM(C14:H14) | J14: ==B14-I14 | K14: Active campaign tracking
